pdfhandoutcrop/__init__.py
pdfhandoutcrop/mainwindow.py
pdfhandoutcrop/pdf.py
pdfhandoutcrop/pdfhandoutcrop.png
pdfhandoutcrop/setlayoutdialog.py
pdfhandoutcrop/ui_mainwindow.py
pdfhandoutcrop/ui_setlayoutdialog.py
pdfhandoutcrop/language/pdfhandoutcrop.ts
pdfhandoutcrop/language/pdfhandoutcrop_it.qm
pdfhandoutcrop/language/pdfhandoutcrop_it.ts
pdfhandoutcrop/language/pdfhandoutcrop_nl.qm
pdfhandoutcrop/language/pdfhandoutcrop_nl.ts
pdfhandoutcrop/language/pdfhandoutcrop_ru.qm
pdfhandoutcrop/language/pdfhandoutcrop_ru.ts
pdfhandoutcrop/language/pdfhandoutcrop_zh_TW.qm
pdfhandoutcrop/language/pdfhandoutcrop_zh_TW.ts
pdfhandoutcrop-0.99.3.data/scripts/pdfhandoutcrop
pdfhandoutcrop-0.99.3.dist-info/LICENSE.txt
pdfhandoutcrop-0.99.3.dist-info/METADATA
pdfhandoutcrop-0.99.3.dist-info/WHEEL
pdfhandoutcrop-0.99.3.dist-info/top_level.txt
pdfhandoutcrop-0.99.3.dist-info/RECORD
