Metadata-Version: 2.1
Name: pdfhandoutcrop
Version: 0.99.3
Summary: A tool to crop pdf handout with multiple pages per sheet
Home-page: https://cges30901.github.io/pdfhandoutcrop/
Download-URL: https://cges30901.github.io/pdfhandoutcrop/download.html
Author: Hsiu-Ming Chang
Author-email: cges30901@gmail.com
License: GPLv3+
Project-URL: Bug Reports, https://github.com/cges30901/pdfhandoutcrop/issues
Project-URL: Source, https://github.com/cges30901/pdfhandoutcrop/
Project-URL: Donate, https://cges30901.github.io/pdfhandoutcrop/donate.html
Keywords: pdf crop
Classifier: Development Status :: 5 - Production/Stable
Classifier: Intended Audience :: Education
Classifier: Intended Audience :: End Users/Desktop
Classifier: Topic :: Education
Classifier: Topic :: Office/Business
Classifier: License :: OSI Approved :: GNU General Public License v3 or later (GPLv3+)
Classifier: Programming Language :: Python :: 3
Classifier: Operating System :: OS Independent
Classifier: Natural Language :: English
Classifier: Natural Language :: Chinese (Traditional)
Requires-Python: >=3
License-File: LICENSE.txt
Requires-Dist: PyQt6
Requires-Dist: PyMuPDF
